pymatops/__init__.py
pymatops/pymatops.py
pymatops-1.3.1.dist-info/LICENSE
pymatops-1.3.1.dist-info/METADATA
pymatops-1.3.1.dist-info/WHEEL
pymatops-1.3.1.dist-info/top_level.txt
pymatops-1.3.1.dist-info/RECORD
