Metadata-Version: 2.1
Name: pymatops
Version: 1.3.1
Summary: A Python package for Matrix Operations
Home-page: https://github.com/yash-seth/pymatops
Author: Yash Seth
Author-email: <yashseth2002@gmail.com>
License: UNKNOWN
Keywords: python,matrix,operations,maths,matrices,mathematics
Platform: UNKNOWN
Classifier: Development Status :: 5 - Production/Stable
Classifier: Intended Audience :: Developers
Classifier: Programming Language :: Python :: 3
Classifier: Operating System :: Unix
Classifier: Operating System :: MacOS :: MacOS X
Classifier: Operating System :: Microsoft :: Windows
